time_guard-0.0.4.dist-info/licenses/LICENSE
time_guardian/__init__.py
time_guardian/__main__.py
time_guardian/_version.py
time_guardian/ai_classifier.py
time_guardian/analyze.py
time_guardian/capture.py
time_guardian/cli.py
time_guardian/monitors.py
time_guardian/mss_enhanced.py
time_guardian/perf.py
time_guardian/processes.py
time_guardian/report.py
time_guardian/storage.py
time_guardian/utils.py
time_guardian/visibility.py
time_guardian/windows.py
time_guard-0.0.4.dist-info/METADATA
time_guard-0.0.4.dist-info/WHEEL
time_guard-0.0.4.dist-info/entry_points.txt
time_guard-0.0.4.dist-info/top_level.txt
time_guard-0.0.4.dist-info/RECORD
