Metadata-Version: 2.4
Name: time-guard
Version: 0.0.4
Summary: Python-based screen activity tracker that captures images every 5 seconds for AI-powered computer usage analysis.
Author: Bryce Drennan
Project-URL: Documentation, https://github.com/brycedrennan/time-guardian
Project-URL: Source, https://github.com/brycedrennan/time-guardian
Requires-Python: >=3.12
License-File: LICENSE
Requires-Dist: pillow
Requires-Dist: typer
Requires-Dist: requests
Requires-Dist: openai
Requires-Dist: numpy
Requires-Dist: mss
Requires-Dist: schedule
Requires-Dist: psutil
Requires-Dist: pyobjc-framework-Quartz; sys_platform == "darwin"
Dynamic: license-file
